setup.py
cad/__init__.py
cad/aes_util.py
cad/app_config_util.py
cad/cad_util.py
cad/exceptions.py
cad/log_util.py
cad/proxy.py
cad/redis_util.py
cad.egg-info/PKG-INFO
cad.egg-info/SOURCES.txt
cad.egg-info/dependency_links.txt
cad.egg-info/not-zip-safe
cad.egg-info/requires.txt
cad.egg-info/top_level.txt
tests/__init__.py
tests/test_aes_util.py
tests/test_app_config_util.py
tests/test_cad_util.py