Metadata-Version: 2.1
Name: cad
Version: 1.1.1
Summary: cache aes authorization decrypter
Home-page: UNKNOWN
Author: Lin Luo / Bruce Liu
Author-email: 15869300264@163.com
License: UNKNOWN
Platform: any
Classifier: Programming Language :: Python :: 3
